{"received":10000,"accepted":3828,"rejected":6190,"succeeded":3810,"failed":0,"mvccFailures":0,"transientRetries":0,"queueWaitTotalMs":2460124,"queueWaitMaxMs":4997,"fabricTotalMs":573421,"fabricMaxMs":5004,"totalTotalMs":3033545,"totalMaxMs":9815,"queueLengthTotal":926146,"queueLengthSamples":7638,"queueLengthMax":150,"readyChecks":1080342,"conflictBlocked":1069738,"scdWindows":8911,"scdSelected":3810,"scdConflictEdges":1742,"scdBypassed":194959,"hotKeyRejected":92,"ttlExpired":18,"adaptiveNormalAccepted":281,"adaptiveLaAccepted":3547,"adaptiveModeSwitches":1,"adaptiveMode":"la","recentQueueWaitAvgMs":1292.703125,"maxPendingByKey":0,"active":0,"activeReadKeys":0,"waiting":0,"pendingWriteKeys":0,"activeWriteKeys":0,"queuedTasks":0,"queueWaitAvgMs":645.7018372703412,"fabricAvgMs":150.5041994750656,"totalAvgMs":796.2060367454068,"queueLengthAvg":121.25504058654099}