{"received":6000,"accepted":4920,"rejected":1080,"succeeded":4920,"failed":0,"mvccFailures":0,"transientRetries":0,"queueWaitTotalMs":2380293,"queueWaitMaxMs":3637,"fabricTotalMs":710431,"fabricMaxMs":2103,"totalTotalMs":3090724,"totalMaxMs":5588,"queueLengthTotal":1011908,"queueLengthSamples":9840,"queueLengthMax":150,"readyChecks":508435,"conflictBlocked":265243,"scdWindows":5321,"scdSelected":4920,"scdConflictEdges":48880,"scdBypassed":52675,"hotKeyRejected":0,"ttlExpired":0,"adaptiveNormalAccepted":1132,"adaptiveLaAccepted":3788,"adaptiveModeSwitches":1,"adaptiveMode":"la","recentQueueWaitAvgMs":2411.140625,"maxPendingByKey":0,"active":0,"activeReadKeys":0,"waiting":0,"pendingWriteKeys":0,"activeWriteKeys":0,"queuedTasks":0,"queueWaitAvgMs":483.79939024390245,"fabricAvgMs":144.39654471544716,"totalAvgMs":628.1959349593496,"queueLengthAvg":102.83617886178862}