{"received":6000,"accepted":4461,"rejected":1561,"succeeded":4439,"failed":0,"mvccFailures":0,"transientRetries":0,"queueWaitTotalMs":2307686,"queueWaitMaxMs":6059,"fabricTotalMs":575277,"fabricMaxMs":2095,"totalTotalMs":2882963,"totalMaxMs":8119,"queueLengthTotal":1020369,"queueLengthSamples":8900,"queueLengthMax":150,"readyChecks":1127662,"conflictBlocked":1111331,"scdWindows":9894,"scdSelected":4439,"scdConflictEdges":2040,"scdBypassed":221982,"hotKeyRejected":14,"ttlExpired":22,"adaptiveNormalAccepted":701,"adaptiveLaAccepted":3760,"adaptiveModeSwitches":1,"adaptiveMode":"la","recentQueueWaitAvgMs":1032.28125,"maxPendingByKey":0,"active":0,"activeReadKeys":0,"waiting":0,"pendingWriteKeys":0,"activeWriteKeys":0,"queuedTasks":0,"queueWaitAvgMs":519.8661860779455,"fabricAvgMs":129.59608019824284,"totalAvgMs":649.4622662761883,"queueLengthAvg":114.64820224719101}