{
  "config": {
    "url": "http://127.0.0.1:8082/submit",
    "clients": 100,
    "tps": 300,
    "duration": 20,
    "accountCount": 1000,
    "hotAccountCount": 500,
    "amount": 1,
    "workload": "w3",
    "batchSize": 2,
    "auditSize": 8,
    "transferPct": 70,
    "auditPct": 20,
    "batchPct": 10,
    "timeoutMs": 240000,
    "maxOutstanding": 10000,
    "maxSockets": 10000,
    "out": "/mnt/c/Users/94847/Documents/paper_2026/results/supporting_10repeats_20260626/2/contention/exp2-contention-w3-traditional-lock-hot500-300tps-rep07-client.json"
  },
  "sent": 6000,
  "localDropped": 0,
  "completed": 6000,
  "statusCounts": {
    "200": 1849,
    "408": 666,
    "429": 3485
  },
  "functionCounts": {
    "Transfer": 4200,
    "AuditAccounts": 1200,
    "BatchTransfer": 600
  },
  "latencyTotalMs": 11510537,
  "latencyMaxMs": 8246,
  "elapsedMs": 27219,
  "sendRate": 300,
  "completionRate": 220.43425548330208,
  "latencyAvgMs": 1918.4228333333333
}