{"received":6000,"accepted":3776,"rejected":2339,"succeeded":3661,"failed":0,"mvccFailures":0,"transientRetries":0,"queueWaitTotalMs":2395922,"queueWaitMaxMs":4976,"fabricTotalMs":393340,"fabricMaxMs":2095,"totalTotalMs":2789262,"totalMaxMs":7033,"queueLengthTotal":940853,"queueLengthSamples":7437,"queueLengthMax":150,"readyChecks":1187668,"conflictBlocked":1165681,"scdWindows":9329,"scdSelected":3661,"scdConflictEdges":1823,"scdBypassed":199726,"hotKeyRejected":280,"ttlExpired":115,"adaptiveNormalAccepted":448,"adaptiveLaAccepted":3328,"adaptiveModeSwitches":1,"adaptiveMode":"la","recentQueueWaitAvgMs":1781.671875,"maxPendingByKey":0,"active":0,"activeReadKeys":0,"waiting":0,"pendingWriteKeys":0,"activeWriteKeys":0,"queuedTasks":0,"queueWaitAvgMs":654.4446872439224,"fabricAvgMs":107.4405900027315,"totalAvgMs":761.8852772466539,"queueLengthAvg":126.50974855452468}