{"received":6000,"accepted":4413,"rejected":1587,"succeeded":4413,"failed":0,"mvccFailures":0,"transientRetries":0,"queueWaitTotalMs":2143669,"queueWaitMaxMs":4866,"fabricTotalMs":636898,"fabricMaxMs":2051,"totalTotalMs":2780567,"totalMaxMs":4977,"queueLengthTotal":924393,"queueLengthSamples":8826,"queueLengthMax":150,"readyChecks":485502,"conflictBlocked":411297,"scdWindows":5198,"scdSelected":4413,"scdConflictEdges":23209,"scdBypassed":132598,"hotKeyRejected":0,"ttlExpired":0,"adaptiveNormalAccepted":982,"adaptiveLaAccepted":3431,"adaptiveModeSwitches":1,"adaptiveMode":"normal","recentQueueWaitAvgMs":607.46875,"maxPendingByKey":0,"active":0,"activeReadKeys":0,"waiting":0,"pendingWriteKeys":0,"activeWriteKeys":0,"queuedTasks":0,"queueWaitAvgMs":485.7622932245638,"fabricAvgMs":144.32313618853388,"totalAvgMs":630.0854294130977,"queueLengthAvg":104.73521414004078}